{
  "title": "มรดกของ Leia",
  "title_status": "AI",
  "dialogues": [
    {
      "text": "ไม่นะ! โอ้ว พระเจ้า ไม่นะ! ไข่ของ Leia!",
      "status": "AI"
    },
    {
      "text": "[ชื่อ] ! คุณต้องช่วยผมนะ! ผมแค่เดินออกจากคอกไปแป๊บเดียวเอง พอกลับมามันก็หายไปแล้ว !",
      "status": "AI"
    },
    {
      "text": "ผม─อะไรหายไปงั้นเหรอ? ไข่น่ะสิ! ขอโทษนะ? คุณแน่ใจเหรอว่าพวกโจโคโบะจะออกไข่อีกใบให้!? โธ่! คุณไม่เข้าใจหรอก─ไข่ใบนี้น่ะมีค่ามากเลยนะ! ผมต้องหามันให้เจอ!",
      "status": "AI"
    },
    {
      "text": "คุณจะช่วยผมใช่ไหม [ชื่อ] ? โอ้ ขอบคุณมากๆ เลยนะ ขอบคุณจริงๆ !",
      "status": "AI"
    },
    {
      "text": "ต้องมีคนขโมยมันไปแน่ๆ ไม่มีคำอธิบายอื่นแล้วล่ะ ผมจะไปค้นทุกซอกทุกมุมของคอกอีกครั้งเพื่อความแน่ใจ ระหว่างที่ผมทำอยู่ ผมคงจะดีใจมากๆ ถ้าคุณช่วยไปถามคนอื่นๆ ดูว่าพวกเขาเห็นอะไรผิดปกติบ้างไหม",
      "status": "AI"
    },
    {
      "text": "ข้าเห็นคนท่าทางแปลกๆ บ้างไหมน่ะเหรอ? นอกเหนือจากเจ้าแล้วน่ะรึ? ไม่นะ ข้าจำไม่ได้เลย",
      "status": "AI"
    },
    {
      "text": "ข้าเห็นคนกำลังทำให้พวกนกสงบลงอยู่นะ แต่ก็แค่มองจากไกลๆ น่ะ ข้าก็นึกว่าเป็น Luquelot ซะอีก...",
      "status": "AI"
    },
    {
      "text": "แต่ถ้าเจ้าบอกว่าเขาไม่อยู่ที่คอกในตอนนั้น... แล้วคนที่อยู่กับพวกโจโคโบะคือใครล่ะ?",
      "status": "AI"
    },
    {
      "text": "ไข่โจโคโบะหายไปงั้นเหรอ? อืม ข้าขอคิดดูก่อนนะ",
      "status": "AI"
    },
    {
      "text": "พอเจ้าพูดขึ้นมา ข้าก็นึกได้ว่าเมื่อกี้พวกโจโคโบะส่งเสียงร้องดังมากเลยล่ะ ดังซะจนข้าต้องรีบวิ่งไปดู เกือบจะชนพ่อค้าเร่ที่เดินผ่านมาซะแล้ว แต่ข้าก็ไม่เจออะไรผิดปกตินะ",
      "status": "AI"
    },
    {
      "text": "หืม? ข้าจะอธิบายลักษณะของพ่อค้าเร่คนนั้นได้ไหมน่ะเหรอ? อ้อ... เขาเป็นชาว Elezen น่ะ─ข้าจำหน้าเขาไม่ได้หรอกนะ ดูท่าทางลุกลี้ลุกลนแปลกๆ โอ้พระเจ้า อย่าบอกนะว่าเขา...? ทำไมข้าไม่เข้าไปซักไซ้เขาให้รู้แล้วรู้รอดไปเลยนะในนรกทั้งเจ็ด!?",
      "status": "AI"
    },
    {
      "text": "เห็นใครทำตัวน่าสงสัยบ้างไหมน่ะเหรอ? เห็นสิ ไอ้หนู / แม่หนู มีผู้ชายคนนึงวิ่งหนีไปทาง Tam-Tara Deepcroft น่ะ",
      "status": "AI"
    },
    {
      "text": "หืม? เจ้าบอกว่ามีไข่หายไปงั้นเหรอ? งั้นข้าว่านั่นแหละคือคนร้ายล่ะ",
      "status": "AI"
    },
    {
      "text": "แต่ทำไมถึงมีคนมาขโมยไข่โจโคโบะล่ะ? ถ้าไม่มีความรู้เรื่องนี้ล่ะก็ แทบจะเป็นไปไม่ได้เลยนะที่จะฟักมันออกมาได้น่ะ",
      "status": "AI"
    },
    {
      "text": "ถ้างั้นก็ไม่มีอะไรผิดพลาดแล้วล่ะ ไข่ถูกขโมยไปจริงๆ ด้วย",
      "status": "AI"
    },
    {
      "text": "และจากสิ่งที่คุณบอกผม นี่ไม่ใช่การโจรกรรมธรรมดาแน่ๆ",
      "status": "AI"
    },
    {
      "text": "การที่คนร้ายขโมยไปแค่ไข่ของ Leia แล้วทิ้งไข่ใบอื่นๆ ไว้ แสดงว่าเรากำลังรับมือกับคนที่เชี่ยวชาญเรื่องการเพาะพันธุ์โจโคโบะ ผมเสียใจที่ต้องบอกว่าผู้ต้องสงสัยคนนี้น่าจะเป็นคนจากบ้านเกิดผมที่ Ishgard นั่นแหละ",
      "status": "AI"
    },
    {
      "text": "คุณรู้ไหม Leia เป็นสายเลือดของ Ouranos—หนึ่งในนกที่ยอดเยี่ยมที่สุดเท่าที่เคยมีมาในคอกของ Ishgard เลยล่ะ",
      "status": "AI"
    },
    {
      "text": "มีคนมากมายในบ้านเกิดผมที่ยอมแลกด้วยแขนขวาเพื่อให้ได้ไข่ของ Leia สักใบ... พระเจ้าเอ๊ย ผมน่าจะมองเรื่องนี้ออกตั้งแต่แรก! เราต้องรีบตามล่าตัวมันเดี๋ยวนี้เลย!",
      "status": "AI"
    },
    {
      "text": "ใจเย็นก่อน Luquelot! ถ้าหัวขโมยไข่นี่มาจาก Ishgard อย่างที่คุณว่า แล้วทำไมมันถึงวิ่งไปทาง Tam-Tara Deepcroft ล่ะ? เว้นแต่ว่าแผนที่ในหัวฉันจะกลับด้านนะ นั่นมันคนละทิศกันเลยนะ",
      "status": "AI"
    },
    {
      "text": "ก-ก็ใช่นะ แต่... เขาอาจจะพยายามทิ้งรอยเท้าปลอมไว้ หรือ... เอ่อ... โธ่เว้ย! เหตุผลมันไม่สำคัญหรอกน่า! สิ่งสำคัญที่สุดคือไข่ของ Leia ต่างหาก! นักผจญภัย ผมขอร้องล่ะ ช่วยตามล่าไอ้สารเลวนั่นแล้วเอาของที่มันขโมยไปกลับคืนมาให้ทีเถอะ!",
      "status": "AI"
    },
    {
      "text": "แหม อย่างน้อยคุณก็ไม่ได้คิดจะไล่ตามเขาไปเองนะ... ไม่ว่าเขาจะมาจากไหนก็ตาม",
      "status": "AI"
    },
    {
      "text": "พวกเราอาจจะสร้างปาฏิหาริย์กับนกของเราได้ก็จริงนะ [ชื่อ] แต่วีรกรรมความกล้าหาญแบบนั้นน่ะ ไม่ใช่ทางถนัดของเราเลย ถ้าคุณไม่ว่าอะไร เราขอปล่อยเรื่องนั้นให้เป็นหน้าที่ของคุณก็แล้วกันนะ",
      "status": "AI"
    },
    {
      "text": "ถ้าโชคดี คุณอาจจะจับขโมยได้บนถนนที่มุ่งไปสู่ Tam-Tara Deepcroft นะ แต่ระวังตัวด้วยล่ะ—เราไม่แน่ใจหรอกนะว่าเขาลงมือคนเดียวหรือเปล่า",
      "status": "AI"
    },
    {
      "text": "<หอบ> <หอบ> ในที่สุดข้าก็จับแกได้สักทีนะ ไอ้ปีศาจร้าย! ส่งไข่มาซะดีๆ !",
      "status": "AI"
    },
    {
      "text": "แกเอาไปไม่ได้หรอก คุโปะ! ไข่ใบนี้เป็นของ Luquelot นะ!",
      "status": "AI"
    },
    {
      "text": "เจ้าเป็นใครมาจากไหนในนรกของ Halone เนี่ย? อ้อ ไอ้พวกขี้ขลาดที่ Bentbranch จ้างนักผจญภัยมาสินะ?",
      "status": "AI"
    },
    {
      "text": "เรื่องยุ่งยากอีกแล้วสิ ละครฉากนี้มันยืดเยื้อมานานพอแล้ว ฆ่าเจ้าม็อกเกิลกับไอ้ลูกจ้างชาวไร่นั่นซะ แล้วเอาไข่บ้านั่นมาให้ข้า!",
      "status": "AI"
    },
    {
      "text": "ขอบคุณนะ คุโปะ",
      "status": "AI"
    },
    {
      "text": "อะไรนะ คุโปะ? ข้ามาอยู่ที่นี่ได้ยังไงงั้นเหรอ?",
      "status": "AI"
    },
    {
      "text": "อ้อ คือว่า ไข่ใบนี้เป็นของ Leia น่ะ เผื่อเจ้าไม่รู้ Leia เป็นโจโคโบะที่พิเศษมากๆ เลยนะ",
      "status": "AI"
    },
    {
      "text": "ยังไงก็ตาม ข้ากำลังงีบหลับอยู่ในคอก ตอนที่ไอ้ชั่วหน้าหนวดนั่นแอบย่องเข้ามาแล้วพยายามจะขโมยมัน คุโปะ!",
      "status": "AI"
    },
    {
      "text": "ข้าก็เลยรีบคว้ามันมาแล้ววิ่งหนีสุดชีวิตเลย ข้าตั้งใจจะเอามันไปคืนที่ Bentbranch Meadows เองนะ แต่ให้เจ้าเอาไปคืนน่าจะปลอดภัยกว่านะ ข้ามั่นใจว่า Luquelot คงจะดีใจมากๆ ที่เห็นเจ้านะ คุโปะ!",
      "status": "AI"
    },
    {
      "text": "คุณได้ไข่มาไหม!? มันปลอดภัยดีหรือเปล่า!?",
      "status": "AI"
    },
    {
      "text": "ใช่ สีก็ใช่ น้ำหนักก็ใช่... นี่คือไข่ของ Leia ไม่ผิดแน่",
      "status": "AI"
    },
    {
      "text": "ผมไม่รู้จะขอบคุณคุณยังไงดีเลยล่ะ",
      "status": "AI"
    },
    {
      "text": "คุณทำฉันเป็นห่วงไปพักนึงเลยนะเนี่ย [ชื่อ] ดีใจจังที่เห็นคุณกับไข่กลับมาอย่างปลอดภัย",
      "status": "AI"
    },
    {
      "text": "...แสดงว่าสมมติฐานของผมที่ว่ามีชาว Ishgard เข้ามาเกี่ยวข้องก็ถูกต้องสินะ—ถึงแม้ว่าคนที่ขโมยไข่ไปจริงๆ จะไม่ใช่เขาก็เถอะ แหม ผมนึกไม่ถึงเลยนะเนี่ยว่าจะมีม็อกเกิลเข้ามาช่วยเราด้วย!",
      "status": "AI"
    },
    {
      "text": "ให้ตายเถอะ... คงไม่ใช่ตัวเดียวกันหรอกมั้ง... ใช่ไหม?",
      "status": "AI"
    },
    {
      "text": "คุณเคยเจอกับผู้ช่วยชีวิตที่ไม่น่าเป็นไปได้คนนี้มาก่อนงั้นหรือ Keitha?",
      "status": "AI"
    },
    {
      "text": "ก็อาจจะใช่ล่ะนะ ม็อกเกิลตัวนึงช่วยชีวิตฉันไว้ตอนที่เกิด Calamity น่ะ",
      "status": "AI"
    },
    {
      "text": "วันนั้นฉันอยู่ในป่าส่วนที่เราเรียกกันว่า Standin' Corses ตอนนี้น่ะ ดูเหมือนว่าป่าทั้งป่าจะถูกไฟไหม้ไปหมดแล้ว และฉันก็มองไม่เห็นอะไรเลยแม้แต่ระยะหลาเดียวเพราะควันไฟ ฉันเกือบจะหมดหวังแล้วล่ะ",
      "status": "AI"
    },
    {
      "text": "แล้วจู่ๆ ม็อกเกิลตัวนึงก็โผล่มาจากไหนก็ไม่รู้ มาดึงแขนเสื้อที่กำลังไหม้ไฟของฉัน แล้วนำทางฉันตรงไปยังส่วนของป่าที่ไฟยังลามไปไม่ถึง",
      "status": "AI"
    },
    {
      "text": "และนั่นก็คือเหตุผลที่ธุรกิจของเราได้ชื่อว่า \"Moogle's Gift Mounts\" ไงล่ะ มันดูเป็นสิ่งที่น้อยที่สุดที่ฉันจะทำได้แล้วล่ะ ฉันคงตายไปแล้วถ้าไม่ได้เจ้าตัวน้อยผู้กล้าหาญนั่นน่ะ",
      "status": "AI"
    },
    {
      "text": "เหลือเชื่อจริงๆ บางทีเจ้าม็อกเกิลนั่นอาจจะคอยเฝ้าดูพวกเรามาตลอดตั้งแต่วันนั้นเลยก็ได้นะ...",
      "status": "AI"
    },
    {
      "text": "ฮ่า! เราควรจะกลับไปทำงานได้แล้วล่ะ ไม่อยากจะทำให้เทวดาผู้พิทักษ์ของเราผิดหวังหรอกใช่ไหมล่ะ? [ชื่อ] ขอขอบคุณคุณมากนะ อ้อ แล้วฉันคิดว่า Luquelot คงอยากจะให้อะไรตอบแทนคุณสำหรับความเหนื่อยยากของคุณน่ะ",
      "status": "AI"
    },
    {
      "text": "ไข่ของ Leia ไม่สามารถหาอะไรมาทดแทนได้เลย ผมไม่รู้จะสรรหาคำพูดไหนมาอธิบายความซาบซึ้งใจของผมได้เลยล่ะ",
      "status": "AI"
    },
    {
      "text": "แต่ถึงอย่างนั้น ผมก็ยังรู้สึกกังวลอยู่ดี... ในขณะที่เรื่องน่าเสียใจทั้งหมดนี้กำลังเกิดขึ้น ผมดันไปเห็นอะไรบางอย่างที่ทำให้ผมกังวลใจมากเลยล่ะ...",
      "status": "AI"
    },
    {
      "text": "ผมบอกหรือยังนะว่าไข่ของ Leia ฟักออกมาแล้ว? เรายังไม่ได้ตั้งชื่อให้เลย แต่ลูกเจี๊ยบก็แข็งแรง ร่าเริง แล้วก็ขี้สงสัยสุดๆ ไปเลย เธอจะได้รับการดูแลอย่างดีที่สุด และจะเติบโตขึ้นเป็นโจโคโบะที่ยอดเยี่ยมแน่นอน",
      "status": "AI"
    }
  ]
}