{
  "title_th": "สายตาที่จับจ้องมาที่ฉัน",
  "dialogues": [
    {
      "text_th": "ฉัน... ฉันไม่ได้คิดไปเองนะ [ชื่อ] ฉันรู้ว่าฉันกำลังถูกจับตามอง..."
    },
    {
      "text_th": "มันต่างออกไป─มีความประสงค์ร้าย มันเหมือนกับว่าฉันกำลัง... ถูกสังเกตการณ์อยู่"
    },
    {
      "text_th": "ความรู้สึกนั้นเดี๋ยวมาเดี๋ยวไป... แต่ฉันรู้สึกได้ตอนที่ออกไปข้างนอกครั้งล่าสุด ใช่ ฉันรู้ว่าฉันรู้สึกแบบนั้น รบกวนช่วยออกไปดูให้ฉันหน่อยได้ไหม... ได้โปรด เถอะนะ? ใช้เวลาแค่แป๊บเดียวเอง"
    },
    {
      "text_th": "คุณถูกโจมตีใช่ไหม? คุณปลอดภัยดีหรือเปล่า? ขอบคุณพระเจ้า"
    },
    {
      "text_th": "ว่าแล้วเชียว เขากำลังจับตาดูฉันอยู่จริงๆ ...แต่ทำไมเขาถึงต้องมาจับตาดูฉันด้วยล่ะ?"
    },
    {
      "text_th": "เขาต้องการอะไรจากฉัน? หรือบางที... เขาอาจจะรู้อะไรเกี่ยวกับอดีตของฉันงั้นเหรอ? ถ้าฉันได้ถามเขาก็ดีสิ..."
    },
    {
      "text_th": "ฉัน... ฉันต้องขอเวลาคิดหน่อย ได้โปรดปล่อยให้ฉันอยู่คนเดียวสักพักเถอะ เดี๋ยวก่อน หลวงพ่อ Iliud ต้องรู้เรื่องนี้ ช่วยบอกท่านแทนฉันทีได้ไหม? มันสำคัญมากนะ ฉันคิดว่าน่าจะมีคนมาตามหาฉันอีกแน่ๆ"
    },
    {
      "text_th": "สวรรค์โปรดเมตตา... เรื่องแบบนี้ไม่ควรเกิดขึ้นในสถานที่ศักดิ์สิทธิ์เลย! เจ้าพอจะรู้ไหมว่าชายผู้นี้เป็นใคร? เจ้าสังเกตเห็นอะไรที่โดดเด่นเกี่ยวกับเครื่องแต่งกายหรือของใช้ของเขาบ้างหรือไม่?"
    },
    {
      "text_th": "นี่... นี่มันเหล็กของพวก Garlean นี่นา ซึ่งก็หมายความว่าคนที่แอบจับตาดู Marques อยู่นั้นคือ..."
    },
    {
      "text_th": "รีบไปที่ Camp Drybone ด่วนเลย! เราต้องไปตาม Immortal Flames มาก่อนที่พวกอิมพีเรียลจะแห่กันมาอีก!"
    },
    {
      "text_th": "ฮึ ฉันอุตส่าห์หวังเอาไว้ว่าจะเป็นคนแรกที่ได้คุยกับคุณ... หวังว่าฉันจะโชคดีขนาดนั้นนะ"
    },
    {
      "text_th": "ตามสบายเถอะนักผจญภัย─ฉันไม่ได้มาในนามของจักรวรรดิหรอกนะ ตรงกันข้ามเลย ฉันตั้งใจจะมาฟื้นฟูกลุ่ม Scions of the Seventh Dawn ต่างหาก"
    },
    {
      "text_th": "และเพื่อการนั้น..."
    },
    {
      "text_th": "ฉันมาตามหาตำนาน─วิศวกรที่ยิ่งใหญ่ที่สุดในยุคของเรา ท่านปรมาจารย์ Cid Garlond ─ฉันมาเพื่อคุณ"
    },
    {
      "text_th": "ฉันเกรงว่าคุณจะเข้าใจผิดแล้วล่ะลูกเอ๋ย เขาเป็นเพียงชายผู้น่าสงสารที่ต้องเป็นพยานรับรู้ความโหดร้ายที่ Carteneau เท่านั้นเอง"
    },
    {
      "text_th": "ฉันขอร้องล่ะ ปล่อยพวกเราไปเถอะ..."
    },
    {
      "text_th": "เดี๋ยวก่อน... ฉัน..."
    },
    {
      "text_th": "ฟังฉันนะ Cid! Eorzea ต้องการคุณ!"
    },
    {
      "text_th": "เธอ... ดูคุ้นเคยจัง... เรา... มัน... เลือนรางไปหมด"
    },
    {
      "text_th": "Cid ใช่ไหม? นี่... ของพวกนี้เป็นของคุณ"
    },
    {
      "text_th": "ฉันคิดว่าคุณต้องมีเครื่องหมายแห่งความยิ่งใหญ่อยู่ในตัวแน่ๆ... ดูเหมือนฉันจะคิดถูกนะ"
    },
    {
      "text_th": "เวลาที่เราได้อยู่ด้วยกันมันช่างสั้นเหลือเกิน แต่ฉันรู้สึกราวกับว่าลูกชายของฉันได้กลับมาหาฉันอีกครั้ง คุณนำความสุขมาสู่ชีวิตของคนแก่คนนี้เลยล่ะ"
    },
    {
      "text_th": "แต่มันถึงเวลาที่คุณต้องไปช่วยคนที่ต้องการคุณจริงๆ แล้วล่ะ"
    },
    {
      "text_th": "คุณ... เป็นใคร?"
    },
    {
      "text_th": "Alphinaud Leveilleur ยินดีรับใช้ครับ"
    },
    {
      "text_th": "ในฐานะของ Scion of the Seventh Dawn ฉันจะยืนหยัดต่อกรกับพวกไพรมอลและพวกอิมพีเรียลที่เป็นศัตรูของเรา─เช่นเดียวกับที่คุณปู่ของฉันเคยทำ"
    },
    {
      "text_th": "ไม่ใช่ความลับเลยว่าเกิดอะไรขึ้นกับกลุ่มของเราที่ Waking Sands ข่าวแพร่สะพัดไปทั่ว Eorzea แล้ว"
    },
    {
      "text_th": "ผลกระทบที่ตามมามันยิ่งใหญ่กว่าที่คุณคิดนะ หลังจากเหตุการณ์ Calamity ทั้งสามประเทศต่างก็มุ่งความสนใจไปที่การฟื้นฟูประเทศเพียงอย่างเดียว"
    },
    {
      "text_th": "ปล่อยให้เหล่า Scions ต้องต่อสู้กับภัยคุกคามจากไพรมอลอย่างโดดเดี่ยว"
    },
    {
      "text_th": "และดูสิ พวกเราแทบจะถูกทำลายล้างจนหมดสิ้น แต่ถึงแม้ประเทศต่างๆ จะไว้อาลัยให้กับการสูญเสียของเรา และละทิ้งความหวังอันน้อยนิดที่หลงเหลืออยู่ เราก็ไม่อาจละทิ้งหน้าที่ของเราได้─โดยเฉพาะในตอนนี้"
    },
    {
      "text_th": "พวก Ixal ได้อัญเชิญ Garuda ออกมาอีกครั้ง และนางก็กำลังทรมานชาวเมือง Coerthas อยู่ในขณะที่เรากำลังพูดอยู่นี้แหละ"
    },
    {
      "text_th": "ความกระหายในการทำลายล้างของนางนั้น เหนือกว่าไพรมอลตนอื่นๆ มากนัก"
    },
    {
      "text_th": "ที่แย่ไปกว่านั้น ในการอวตารครั้งปัจจุบันนี้ เพื่อนร่วมงานชาว Baldesion ของเราเชื่อว่านางมีพลังเหนือกว่าทั้ง Ifrit และ Titan เสียอีก"
    },
    {
      "text_th": "แต่นั่นก็เป็นโอกาสทองเลยนะ หากเราสามารถเอาชนะ Garuda ได้ มันจะเป็นคำเตือนแก่ชนเผ่าคนเถื่อนอื่นๆ ว่าแม้แต่พระเจ้าที่แข็งแกร่งที่สุดของพวกมันก็สามารถถูกโค่นล้มได้เช่นกัน"
    },
    {
      "text_th": "ถ้าเราจะไปเผชิญหน้ากับศัตรู เราต้องฝ่าพายุที่ปกป้องวิหารของนางไปให้ได้เสียก่อน"
    },
    {
      "text_th": "และสำหรับภารกิจนั้น เราต้องการเรือเหาะ─เรือเหาะของ คุณ Cid"
    },
    {
      "text_th": "ฉัน... ฉันมี... เรือเหาะเหรอ?"
    },
    {
      "text_th": "ใช่ Cid คุณมีเรือเหาะ เรือเหาะของคุณเอง"
    },
    {
      "text_th": "มีคนเห็นมันครั้งสุดท้ายบนท้องฟ้าเหนือกริดาเนีย ก่อนเกิดเหตุการณ์ Calamity ไม่นาน งั้นเรามาเริ่มตามหากันที่นั่นเถอะ"
    },
    {
      "text_th": "ร-เรือเหาะ...? เรือเหาะของฉัน...?"
    },
    {
      "text_th": "ด-เดี๋ยวก่อน..."
    },
    {
      "text_th": "มาเถอะ ไปจัดการพวกไพรมอลให้สิ้นซากกัน! เมื่อเราร่วมมือกัน เราจะแสดงให้โลกเห็นว่า Scions ยังคงเป็นกองกำลังที่น่าเกรงขามอยู่!"
    },
    {
      "text_th": "พวกเขาต้องการเรือเหาะของฉัน... พวกเขาต้องการ... ฉัน"
    }
  ]
}